README.rst
setup.py
PyMapia.egg-info/PKG-INFO
PyMapia.egg-info/SOURCES.txt
PyMapia.egg-info/dependency_links.txt
PyMapia.egg-info/requires.txt
PyMapia.egg-info/top_level.txt
pymapia/__init__.py