Metadata-Version: 1.1
Name: PyMapia
Version: 0.1.1
Summary: Python SDK for WikiMapia (http://wikimapia.org)
Home-page: https://github.com/boisei0/pymapia
Author: Rob Derksen
Author-email: rob.derksen@hubsec.eu
License: MIT
Keywords: sdk api maps wiki
Platform: UNKNOWN
Classifier: Development Status :: 4 - Beta
Classifier: Intended Audience :: Developers
Classifier: License :: OSI Approved :: MIT License
Classifier: Programming Language :: Python :: 2.7
